danbotstatus/__init__.py
danbotstatus/asynchronous.py
danbotstatus/errors.py
danbotstatus/synchronous.py
danbot_status-0.2.1.dist-info/LICENSE
danbot_status-0.2.1.dist-info/METADATA
danbot_status-0.2.1.dist-info/WHEEL
danbot_status-0.2.1.dist-info/top_level.txt
danbot_status-0.2.1.dist-info/RECORD
