Metadata-Version: 2.1
Name: danbot-status
Version: 0.2.1
Summary: Status Of All Services of DanBotHost(DBH)
Home-page: https://github.com/VineyS/danbot-status-py
Author: VineyS
Author-email: vineypsunu@gmail.com
Classifier: Programming Language :: Python :: 3
Classifier: License :: OSI Approved :: MIT License
Classifier: Operating System :: OS Independent
Requires-Python: >=3.6
License-File: LICENSE
Requires-Dist: aiohttp (<3.8.0,>=3.6.0)
Requires-Dist: requests (<3.0.0,>=2.22.0)
